<?xml version="1.0" encoding="UTF-8"?>
<objects serializationModel="Studio.02.02.00">
	<object class="AudioFile" id="{30779ca5-1fc4-4d7f-be34-1d4a8d501113}">
		<property name="assetPath">
			<value>HitEnemy1.wav</value>
		</property>
		<property name="frequencyInKHz">
			<value>48</value>
		</property>
		<property name="channelCount">
			<value>2</value>
		</property>
		<property name="length">
			<value>0.45091666666666669</value>
		</property>
		<relationship name="masterAssetFolder">
			<destination>{d38651de-9c61-4b2e-9305-d4b75f132259}</destination>
		</relationship>
	</object>
</objects>
